auto_audio_rec/__init__.py
auto_audio_rec/frontend/index.html
auto_audio_rec/frontend/main.js
auto_audio_rec/frontend/streamlit-component-lib.js
auto_audio_rec/frontend/style.css
auto_audio_rec-0.1.0.dist-info/LICENSE
auto_audio_rec-0.1.0.dist-info/METADATA
auto_audio_rec-0.1.0.dist-info/WHEEL
auto_audio_rec-0.1.0.dist-info/top_level.txt
auto_audio_rec-0.1.0.dist-info/RECORD
